README.md
setup.py
cowsnphr/__init__.py
cowsnphr/cowsnphr.py
legacy_comparison/__init__.py
legacy_comparison/comparer.py
vsnp/__init__.py
vsnp/install_dependencies.py
vsnp/vSNP.py
vsnp/vsnp_tree_methods.py
vsnp/vsnp_tree_run.py
vsnp/vsnp_vcf_methods.py
vsnp/vsnp_vcf_run.py
vsnpdev.egg-info/PKG-INFO
vsnpdev.egg-info/SOURCES.txt
vsnpdev.egg-info/dependency_links.txt
vsnpdev.egg-info/top_level.txt