Metadata-Version: 1.0
Name: vsnpdev
Version: 0.0.21
Summary: USDA APHIS Veterinary Services (VS) Mycobacterium tuberculosis complex, mainly M. bovis, and Brucella sp. SNP pipeline. Genotyping from whole genome sequence (WGS) outputting BAM, VCF, SNP tables and phylogentic trees.
Home-page: https://github.com/USDA-VS/vSNP
Author: Adam Koziol
Author-email: adam.koziol@canada.ca
License: MIT
Platform: UNKNOWN
